hatch/__init__.py
hatch/__main__.py
hatch/_version.py
hatch/py.typed
hatch/cli/__init__.py
hatch/cli/application.py
hatch/cli/terminal.py
hatch/cli/build/__init__.py
hatch/cli/clean/__init__.py
hatch/cli/config/__init__.py
hatch/cli/dep/__init__.py
hatch/cli/env/__init__.py
hatch/cli/env/create.py
hatch/cli/env/find.py
hatch/cli/env/prune.py
hatch/cli/env/remove.py
hatch/cli/env/run.py
hatch/cli/env/show.py
hatch/cli/fmt/__init__.py
hatch/cli/fmt/core.py
hatch/cli/new/__init__.py
hatch/cli/new/migrate.py
hatch/cli/project/__init__.py
hatch/cli/project/metadata.py
hatch/cli/publish/__init__.py
hatch/cli/python/__init__.py
hatch/cli/python/find.py
hatch/cli/python/install.py
hatch/cli/python/remove.py
hatch/cli/python/show.py
hatch/cli/python/update.py
hatch/cli/run/__init__.py
hatch/cli/self/__init__.py
hatch/cli/self/report.py
hatch/cli/self/restore.py
hatch/cli/self/update.py
hatch/cli/shell/__init__.py
hatch/cli/status/__init__.py
hatch/cli/test/__init__.py
hatch/cli/test/core.py
hatch/cli/version/__init__.py
hatch/config/__init__.py
hatch/config/constants.py
hatch/config/model.py
hatch/config/user.py
hatch/config/utils.py
hatch/env/__init__.py
hatch/env/context.py
hatch/env/system.py
hatch/env/utils.py
hatch/env/virtual.py
hatch/env/collectors/__init__.py
hatch/env/collectors/custom.py
hatch/env/collectors/default.py
hatch/env/collectors/plugin/__init__.py
hatch/env/collectors/plugin/hooks.py
hatch/env/collectors/plugin/interface.py
hatch/env/internal/__init__.py
hatch/env/internal/build.py
hatch/env/internal/static_analysis.py
hatch/env/internal/test.py
hatch/env/internal/uv.py
hatch/env/plugin/__init__.py
hatch/env/plugin/hooks.py
hatch/env/plugin/interface.py
hatch/errors/__init__.py
hatch/index/__init__.py
hatch/index/core.py
hatch/index/errors.py
hatch/index/publish.py
hatch/plugin/__init__.py
hatch/plugin/constants.py
hatch/plugin/manager.py
hatch/plugin/specs.py
hatch/plugin/utils.py
hatch/project/__init__.py
hatch/project/config.py
hatch/project/core.py
hatch-1.15.0.dist-info/METADATA
hatch-1.15.0.dist-info/WHEEL
hatch-1.15.0.dist-info/entry_points.txt
hatch-1.15.0.dist-info/licenses/LICENSE.txt
hatch-1.15.0.dist-info/RECORD
