Metadata-Version: 2.4
Name: hatch
Version: 1.15.0
Summary: Modern, extensible Python project management
Project-URL: Homepage, https://hatch.pypa.io/latest/
Project-URL: Sponsor, https://github.com/sponsors/ofek
Project-URL: History, https://hatch.pypa.io/dev/history/hatch/
Project-URL: Tracker, https://github.com/pypa/hatch/issues
Project-URL: Source, https://github.com/pypa/hatch
Author-email: Ofek Lev <oss@ofek.dev>
License-Expression: MIT
License-File: LICENSE.txt
Keywords: build,dependency,environment,hatch,packaging,plugin,publishing,release,versioning
Classifier: Development Status :: 5 - Production/Stable
Classifier: Intended Audience :: Developers
Classifier: License :: OSI Approved :: MIT License
Classifier: Natural Language :: English
Classifier: Operating System :: OS Independent
Classifier: Programming Language :: Python :: 3.9
Classifier: Programming Language :: Python :: 3.10
Classifier: Programming Language :: Python :: 3.11
Classifier: Programming Language :: Python :: 3.12
Classifier: Programming Language :: Python :: 3.13
Classifier: Programming Language :: Python :: 3.14
Classifier: Programming Language :: Python :: Implementation :: CPython
Classifier: Programming Language :: Python :: Implementation :: PyPy
Classifier: Topic :: Software Development :: Build Tools
Requires-Python: >=3.9
Requires-Dist: click>=8.0.6
Requires-Dist: hatchling>=1.26.3
Requires-Dist: httpx>=0.22.0
Requires-Dist: hyperlink>=21.0.0
Requires-Dist: keyring>=23.5.0
Requires-Dist: packaging>=23.2
Requires-Dist: pexpect~=4.8
Requires-Dist: platformdirs>=2.5.0
Requires-Dist: rich>=11.2.0
Requires-Dist: shellingham>=1.4.0
Requires-Dist: tomli-w>=1.0
Requires-Dist: tomlkit>=0.11.1
Requires-Dist: userpath~=1.7
Requires-Dist: uv>=0.5.23
Requires-Dist: virtualenv>=20.26.6
Requires-Dist: zstandard<1
